chatroom.py
pychatroom-0.2.6.dist-info/METADATA
pychatroom-0.2.6.dist-info/WHEEL
pychatroom-0.2.6.dist-info/entry_points.txt
pychatroom-0.2.6.dist-info/top_level.txt
pychatroom-0.2.6.dist-info/RECORD
