Metadata-Version: 2.1
Name: pychatroom
Version: 0.2.6
Requires-Dist: prompt-toolkit (==3.0.17)
